{
  "$schema": "https://schema.management.azure.com/schemas/2019-04-01/deploymentParameters.json#",
  "contentVersion": "1.0.0.0",
  "parameters": {
    "subscriptionId": {
      "value": "2cd617ea-1866-46b1-90e3-fffb087ebf9b"
    },
    "groupSuffix": {
      "value": "prod"
    },
    "clusterName": {
      "value": "stress-prod"
    },
    "clusterLocation": {
      "value": "westus2"
    },
    "monitoringLocation": {
      "value": "centralus"
    },
    "staticTestSecretsKeyvaultName": {
      "value": "stress-secrets-prod"
    },
    "staticTestSecretsKeyvaultGroup": {
      "value": "rg-stress-secrets-prod"
    },
    "enableMonitoring": {
        "value": true
    },
    "tags": {
      "value": {
        "environment": "Prod",
        "owners": "bebroder"
      }
    }
  }
}
